vibeatlas_ship/__init__.py
vibeatlas_ship/client.py
vibeatlas_ship/exceptions.py
vibeatlas_ship/py.typed
vibeatlas_ship/types.py
vibeatlas_ship-0.1.0b0.dist-info/METADATA
vibeatlas_ship-0.1.0b0.dist-info/WHEEL
vibeatlas_ship-0.1.0b0.dist-info/entry_points.txt
vibeatlas_ship-0.1.0b0.dist-info/licenses/LICENSE
vibeatlas_ship-0.1.0b0.dist-info/RECORD
