Metadata-Version: 2.4
Name: vibeatlas-ship
Version: 0.1.0b0
Summary: SHIP Protocol SDK - Success Heuristics for Intelligent Programming. Measure AI coding reliability.
Project-URL: Homepage, https://ship.vibeatlas.dev
Project-URL: Documentation, https://vibeatlas.dev/docs/ship
Project-URL: Repository, https://github.com/vibeatlas/ship-protocol
Project-URL: Issues, https://github.com/vibeatlas/ship-protocol/issues
Project-URL: Changelog, https://github.com/vibeatlas/ship-protocol/blob/main/CHANGELOG.md
Author-email: VibeAtlas <ship@vibeatlas.dev>
Maintainer-email: VibeAtlas Team <team@vibeatlas.dev>
License-Expression: MIT
License-File: LICENSE
Keywords: ai,ai-coding,claude,code-quality,coding,context-optimization,cursor,developer-tools,github-copilot,llm,reliability,ship-protocol,ship-score,vibeatlas
Classifier: Development Status :: 4 - Beta
Classifier: Intended Audience :: Developers
Classifier: License :: OSI Approved :: MIT License
Classifier: Operating System :: OS Independent
Classifier: Programming Language :: Python :: 3
Classifier: Programming Language :: Python :: 3.9
Classifier: Programming Language :: Python :: 3.10
Classifier: Programming Language :: Python :: 3.11
Classifier: Programming Language :: Python :: 3.12
Classifier: Topic :: Software Development
Classifier: Topic :: Software Development :: Quality Assurance
Classifier: Topic :: Software Development :: Testing
Classifier: Typing :: Typed
Requires-Python: >=3.9
Requires-Dist: httpx>=0.25.0
Requires-Dist: pydantic>=2.0.0
Provides-Extra: dev
Requires-Dist: mypy>=1.0.0; extra == 'dev'
Requires-Dist: pytest-asyncio>=0.21.0; extra == 'dev'
Requires-Dist: pytest-cov>=4.0.0; extra == 'dev'
Requires-Dist: pytest>=7.0.0; extra == 'dev'
Requires-Dist: respx>=0.20.0; extra == 'dev'
Requires-Dist: ruff>=0.1.0; extra == 'dev'
Provides-Extra: langchain
Requires-Dist: langchain-core>=0.1.0; extra == 'langchain'
Requires-Dist: langchain>=0.1.0; extra == 'langchain'
